changeseq/__init__.py
changeseq/alignReads.py
changeseq/callVariants.py
changeseq/changeseq.py
changeseq/findCleavageSites.py
changeseq/log.py
changeseq/mergeReads.py
changeseq/referenceFree.py
changeseq/refseq_gene_name.py
changeseq/utility.py
changeseq/validation.py
changeseq/visualization.py
changeseq-1.2.9.1.data/scripts/alignReads.py
changeseq-1.2.9.1.data/scripts/callVariants.py
changeseq-1.2.9.1.data/scripts/changeseq.py
changeseq-1.2.9.1.data/scripts/findCleavageSites.py
changeseq-1.2.9.1.data/scripts/log.py
changeseq-1.2.9.1.data/scripts/mergeReads.py
changeseq-1.2.9.1.data/scripts/referenceFree.py
changeseq-1.2.9.1.data/scripts/refseq_gene_name.py
changeseq-1.2.9.1.data/scripts/utility.py
changeseq-1.2.9.1.data/scripts/validation.py
changeseq-1.2.9.1.data/scripts/visualization.py
data/__init__.py
data/refseq_gene_name.py
scripts/__init__.py
scripts/test.py
scripts/test_align.py
scripts/test_ga.py
test/__init__.py
test/test_circleseq_merged.py
test/test_circleseq_std.py
test/utils.py
changeseq-1.2.9.1.dist-info/LICENSE
changeseq-1.2.9.1.dist-info/METADATA
changeseq-1.2.9.1.dist-info/WHEEL
changeseq-1.2.9.1.dist-info/top_level.txt
changeseq-1.2.9.1.dist-info/RECORD
