Metadata-Version: 2.1
Name: changeseq
Version: 1.2.9.1
Summary: Bioinformatic pipeline for the CHANGE-seq assay.
Home-page: https://github.com/tsailabSJ/changeseq
Author: Shengdar Q Tsai, Martin Aryee, Ved V Topkar, Jose Malagon-Lopez
Author-email: STSAI4@mgh.harvard.edu, Aryee.Martin@mgh.harvard.edu, vedtopkar@gmail.com, jose.lopez@mail.harvard.edu
License: LICENSE
Keywords: changeseq
Platform: UNKNOWN
Classifier: Development Status :: 4 - Beta
Classifier: Intended Audience :: Science/Research
Classifier: Topic :: Scientific/Engineering :: Bio-Informatics
Classifier: Topic :: Scientific/Engineering :: Visualization
Classifier: Topic :: Scientific/Engineering :: Information Analysis
Classifier: License :: OSI Approved :: GNU General Public License v2 (GPLv2)
Classifier: Operating System :: Unix
Classifier: Natural Language :: English
Classifier: Programming Language :: Python :: 2
Classifier: Programming Language :: Python :: 2.6
Classifier: Programming Language :: Python :: 2.7
